perceptron_emulator/__init__.py
perceptron_emulator/config.py
perceptron_emulator/logic.py
perceptron_emulator/main.py
perceptron_emulator/pattern_library.py
perceptron_emulator/plotting.py
perceptron_emulator/training.py
perceptron_emulator/widgets.py
perceptron_emulator-1.4.1.dist-info/licenses/LICENSE
perceptron_emulator-1.4.1.dist-info/METADATA
perceptron_emulator-1.4.1.dist-info/WHEEL
perceptron_emulator-1.4.1.dist-info/entry_points.txt
perceptron_emulator-1.4.1.dist-info/top_level.txt
perceptron_emulator-1.4.1.dist-info/RECORD
