Metadata-Version: 2.4
Name: perceptron-emulator
Version: 1.4.1
Summary: A GUI-based physical perceptron emulator with custom hardware-style widgets
Home-page: https://github.com/rexackermann/perceptron-emulator
Author: Rex Ackermann
Author-email: 
License: MIT
Project-URL: Homepage, https://github.com/rexackermann/perceptron-emulator
Project-URL: Repository, https://github.com/rexackermann/perceptron-emulator
Project-URL: Bug Tracker, https://github.com/rexackermann/perceptron-emulator/issues
Keywords: perceptron,neural-network,machine-learning,gui,education
Classifier: Development Status :: 4 - Beta
Classifier: Intended Audience :: Education
Classifier: Intended Audience :: Science/Research
Classifier: Topic :: Scientific/Engineering :: Artificial Intelligence
Classifier: License :: OSI Approved :: MIT License
Classifier: Programming Language :: Python :: 3
Classifier: Programming Language :: Python :: 3.9
Classifier: Programming Language :: Python :: 3.10
Classifier: Programming Language :: Python :: 3.11
Classifier: Programming Language :: Python :: 3.12
Classifier: Operating System :: OS Independent
Requires-Python: >=3.9
License-File: LICENSE
Requires-Dist: PyQt6>=6.0.0
Requires-Dist: numpy>=1.20.0
Requires-Dist: matplotlib>=3.5.0
Dynamic: home-page
Dynamic: license-file
Dynamic: requires-python
